<?xml version="1.0" encoding="UTF-8"?>
<song xmlns="http://www.strehle.de/xmlns/ldb" xmlns:xlink="http://www.w3.org/1999/xlink" id="song-1678">
  <title>Danket dem Herrn, denn Er ist freundlich</title>
  <subtitle/>
  <right/>
  <textcopyright>reserved</textcopyright>
  <ccli_number/>
  <comment/>
  <language>de</language>
  <copyrightyear/>
  <ccli_features/>
  <author xlink:href="#artist-9924" xlink:type="simple">
    <part>Music</part>
    <year>1948</year>
  </author>
  <songbookref xlink:href="#songbook-87" xlink:type="simple">
    <numinsongbook>474</numinsongbook>
    <notes>1</notes>
    <chords>0</chords>
    <several_voices>0</several_voices>
  </songbookref>
  <keyword xlink:href="#keyword-10155" xlink:type="simple"/>
  <bibleref xlink:href="#biblechapter-psa-106" xlink:type="simple">
    <verse>1</verse>
  </bibleref>
</song>
