<?xml version="1.0" encoding="UTF-8"?>
<songbook xmlns="http://www.strehle.de/xmlns/ldb" xmlns:xlink="http://www.w3.org/1999/xlink" id="songbook-9162">
  <name>Jesu Name nie verklinget 3</name>
  <icon xlink:href="#file-9161" xlink:type="simple"/>
  <comment>Altes und neues erweckliches Lied.
Herausgegeben von Pfr. Dr. theol. Otto Riecker
Hänssler-Verlag, Neuhausen-Stuttgart.

http://www.liederdatenbank.de/songbook/563 - Lied Nr. 0001 bis 0260
http://www.liederdatenbank.de/songbook/9160 - Lied Nr. 0261 bis 0627
http://www.liederdatenbank.de/songbook/9162 - Lied Nr. 0628 bis 0913
http://www.liederdatenbank.de/songbook/9164 - Lied Nr. 0914 bis 1240
http://www.liederdatenbank.de/songbook/9166 - Lied Nr. 1241 bis 1534
http://www.liederdatenbank.de/songbook/9168 - Lied Nr. 1535 bis 1824

*** Dieses Liederbuch ist noch nicht vollständig in der Liederdatenbank erfaßt. ***</comment>
  <state>1</state>
  <code/>
  <url xlink:href="http://www.amazon.de/exec/obidos/ASIN/3775103171" xlink:type="simple">
    <title>Jesu Name nie verklinget 3 @ Amazon.de</title>
  </url>
  <url xlink:href="http://www.booklooker.de/app/result.php?titel=Jesu+Name+nie+verklinget" xlink:type="simple">
    <title>Jesu Name nie verklinget @ Booklooker.de</title>
  </url>
  <url xlink:href="http://search.ebay.de/Jesu-Name-nie-verklinget" xlink:type="simple">
    <title>Jesu Name nie verklinget @ eBay.de</title>
  </url>
</songbook>
