<?xml version="1.0" encoding="UTF-8"?>
<song xmlns="http://www.strehle.de/xmlns/ldb" xmlns:xlink="http://www.w3.org/1999/xlink" id="song-10774">
  <title>Du bist der Herr</title>
  <subtitle>Menschen kommen, Menschen gehen</subtitle>
  <right>Felsenfest Musikverlag, Wesel</right>
  <textcopyright>reserved</textcopyright>
  <ccli_number/>
  <comment/>
  <language>de</language>
  <copyrightyear/>
  <ccli_features/>
  <author xlink:href="#artist-55" xlink:type="simple">
    <part>Text</part>
    <year/>
  </author>
  <author xlink:href="#artist-77" xlink:type="simple">
    <part>Music</part>
    <year/>
  </author>
  <songbookref xlink:href="#songbook-10768" xlink:type="simple">
    <numinsongbook>11</numinsongbook>
    <notes>1</notes>
    <chords>1</chords>
    <several_voices>0</several_voices>
  </songbookref>
  <keyword xlink:href="#keyword-10156" xlink:type="simple"/>
</song>
