<?xml version="1.0" encoding="UTF-8"?>
<song xmlns="http://www.strehle.de/xmlns/ldb" xmlns:xlink="http://www.w3.org/1999/xlink" id="song-1220">
  <title>When all my labors and trials are over</title>
  <subtitle>O that will be glory for me</subtitle>
  <language>en</language>
  <copyrightyear/>
  <right/>
  <textcopyright>reserved</textcopyright>
  <ccli_number/>
  <comment/>
  <ccli_features/>
  <author xlink:href="#artist-4521" xlink:type="simple">
    <part>TextMusic</part>
    <year>1900/1903</year>
  </author>
  <songbookref xlink:href="#songbook-89" xlink:type="simple">
    <numinsongbook>358</numinsongbook>
    <notes>1</notes>
    <chords>1</chords>
    <several_voices>1</several_voices>
  </songbookref>
  <keyword xlink:href="#keyword-10157" xlink:type="simple"/>
  <keyword xlink:href="#keyword-25074" xlink:type="simple"/>
</song>
