<?xml version="1.0" encoding="UTF-8"?>
<song xmlns="http://www.strehle.de/xmlns/ldb" xmlns:xlink="http://www.w3.org/1999/xlink" id="song-1168">
  <title>Vom Himmel kam Er zu uns</title>
  <subtitle>Du großer König Jesus Christ</subtitle>
  <language>de</language>
  <textcopyright>reserved</textcopyright>
  <ccli_number/>
  <comment/>
  <copyrightyear/>
  <right/>
  <publisher xlink:href="#publisher-10865" xlink:type="simple"/>
  <author xlink:href="#artist-45" xlink:type="simple">
    <part>TextMusic</part>
    <year/>
  </author>
  <songbookref xlink:href="#songbook-89" xlink:type="simple">
    <numinsongbook>293</numinsongbook>
    <notes>1</notes>
    <chords>1</chords>
    <several_voices>0</several_voices>
  </songbookref>
  <keyword xlink:href="#keyword-4835" xlink:type="simple"/>
</song>
