<?xml version="1.0" encoding="UTF-8"?>
<song xmlns="http://www.strehle.de/xmlns/ldb" xmlns:xlink="http://www.w3.org/1999/xlink" id="song-12133">
  <title>Singt dem Herren</title>
  <subtitle/>
  <copyrightyear>1986</copyrightyear>
  <right>Rechte beim Verfasser</right>
  <textcopyright>reserved</textcopyright>
  <ccli_number/>
  <comment/>
  <language>de</language>
  <author xlink:href="#artist-12132" xlink:type="simple">
    <part>Music</part>
    <year/>
  </author>
  <songbookref xlink:href="#songbook-9501" xlink:type="simple">
    <numinsongbook>12</numinsongbook>
    <notes>1</notes>
    <chords>1</chords>
    <several_voices>0</several_voices>
  </songbookref>
  <bibleref xlink:href="#biblechapter-psa-36" xlink:type="simple">
    <verse>5-6</verse>
  </bibleref>
</song>
