<?xml version="1.0" encoding="UTF-8"?>
<song xmlns="http://www.strehle.de/xmlns/ldb" xmlns:xlink="http://www.w3.org/1999/xlink" id="song-9023">
  <title>Wenn der Sturm kommt</title>
  <subtitle/>
  <right>1999 D&amp;D Medien, D-88287 Grünkraut</right>
  <textcopyright>reserved</textcopyright>
  <comment/>
  <language>de</language>
  <author xlink:href="#artist-51" xlink:type="simple">
    <part>TextMusic</part>
    <year>1999</year>
  </author>
  <songbookref xlink:href="#songbook-9018" xlink:type="simple">
    <numinsongbook>28</numinsongbook>
    <notes>0</notes>
    <chords>0</chords>
    <several_voices>0</several_voices>
  </songbookref>
</song>
