<?xml version="1.0" encoding="UTF-8"?>
<song xmlns="http://www.strehle.de/xmlns/ldb" xmlns:xlink="http://www.w3.org/1999/xlink" id="song-2560">
  <title>Herr des Friedens, komm</title>
  <author xlink:href="#artist-2579" xlink:type="simple">
    <part>TextMusic</part>
    <year>2001</year>
  </author>
  <language>de</language>
  <songbookref xlink:href="#songbook-2273" xlink:type="simple">
    <numinsongbook>252</numinsongbook>
  </songbookref>
  <publisher xlink:href="#publisher-10865" xlink:type="simple"/>
</song>
