<?xml version="1.0" encoding="UTF-8"?>
<songbook xmlns="http://www.strehle.de/xmlns/ldb" xmlns:xlink="http://www.w3.org/1999/xlink" id="songbook-14067">
  <name>Send a Revival</name>
  <comment>Helmut Jost and Gospelfire: "Send a Revival" (Songbook)

Creative Kirche Medien GmbH - Sandstraße 12 - 58455 Witten
Songbook Nr. 140 450 035. - 1. Auflage 2006.</comment>
  <state>1</state>
  <icon xlink:href="#file-14066" xlink:type="simple"/>
  <url xlink:href="http://www.helmutjost.de/" xlink:type="simple"/>
  <url xlink:href="http://www.gospel-fire.de/" xlink:type="simple"/>
  <url xlink:href="http://www.creative-kirche.de/" xlink:type="simple">
    <title>Creative Kirche</title>
  </url>
  <url xlink:href="http://www.gerth.de/?vp_id=www-Link&amp;fct=search&amp;nav_fct=search&amp;search_str=851081" xlink:type="simple">
    <title>Send a Revival (Songbook) @ Gerth.de</title>
  </url>
  <url xlink:href="http://www.haenssler.de/produkt/titel/send-a-revival-klavierausgabe/100252/100252/100252.html" xlink:type="simple">
    <title>Send a Revival (Klavierausgabe) @ Haenssler.de</title>
  </url>
</songbook>
