<?xml version="1.0" encoding="UTF-8"?>
<song xmlns="http://www.strehle.de/xmlns/ldb" xmlns:xlink="http://www.w3.org/1999/xlink" id="song-18930">
  <title>Hey, das ist ein Tag</title>
  <subtitle/>
  <copyrightyear>2004</copyrightyear>
  <right/>
  <textcopyright>reserved</textcopyright>
  <ccli_number/>
  <comment/>
  <language>de</language>
  <publisher xlink:href="#publisher-10865" xlink:type="simple"/>
  <author xlink:href="#artist-14377" xlink:type="simple">
    <part>Text</part>
    <year/>
  </author>
  <author xlink:href="#artist-14376" xlink:type="simple">
    <part>Music</part>
    <year/>
  </author>
  <songbookref xlink:href="#songbook-14340" xlink:type="simple">
    <numinsongbook>7</numinsongbook>
    <notes>1</notes>
    <chords>1</chords>
    <several_voices>0</several_voices>
  </songbookref>
  <keyword xlink:href="#keyword-436" xlink:type="simple"/>
</song>
