<?xml version="1.0" encoding="UTF-8"?>
<song xmlns="http://www.strehle.de/xmlns/ldb" xmlns:xlink="http://www.w3.org/1999/xlink" id="song-23575">
  <title>Gott segne dich</title>
  <subtitle/>
  <copyrightyear/>
  <right>Claudius Verlag, München</right>
  <textcopyright>reserved</textcopyright>
  <ccli_number/>
  <comment/>
  <language>de</language>
  <ccli_features/>
  <author xlink:href="#artist-23573" xlink:type="simple">
    <part>Text</part>
    <year/>
  </author>
  <author xlink:href="#artist-23574" xlink:type="simple">
    <part>Music</part>
    <year/>
  </author>
  <songbookref xlink:href="#songbook-22196" xlink:type="simple">
    <numinsongbook>0109</numinsongbook>
    <notes>1</notes>
    <chords>1</chords>
    <several_voices>0</several_voices>
  </songbookref>
  <keyword xlink:href="#keyword-101" xlink:type="simple"/>
</song>
