<?xml version="1.0" encoding="UTF-8"?>
<songbook xmlns="http://www.strehle.de/xmlns/ldb" xmlns:xlink="http://www.w3.org/1999/xlink" id="songbook-14342">
  <name>Sing mit, lobe den Herrn!</name>
  <comment>Liederbuch für die Kinderstunde
Christlicher Missions-Verlag, Bielefeld 2006, Best.-Nr. 30868.
ISBN 3-932308-68-9.

139 Lieder (Text, mit Akkorden, ohne Noten)</comment>
  <state>1</state>
  <icon xlink:href="#file-14341" xlink:type="simple"/>
  <url xlink:href="http://www.haenssler.de/show.sxp/haenssler_de.html?art_id=100830" xlink:type="simple">
    <title>Sing mit, lobe den Herrn! @ Haenssler.de</title>
  </url>
  <url xlink:href="http://www.leseplatz.de/cgi-bin/navigation/rm/chooseDetailItem/itemID/4362/title/Sing_mit,_lobe_den_Herrn/" xlink:type="simple">
    <title>Sing mit, lobe den Herrn! @ Leseplatz.de</title>
  </url>
</songbook>
